aiolip/__init__.py
aiolip/data.py
aiolip/exceptions.py
aiolip/protocol.py
aiolip-1.1.6.dist-info/AUTHORS.rst
aiolip-1.1.6.dist-info/LICENSE
aiolip-1.1.6.dist-info/METADATA
aiolip-1.1.6.dist-info/WHEEL
aiolip-1.1.6.dist-info/top_level.txt
aiolip-1.1.6.dist-info/RECORD
