Metadata-Version: 2.1
Name: aiolip
Version: 1.1.6
Summary: Async Lutron Integration Protocol
Home-page: https://github.com/bdraco/aiolip
Author: J. Nick Koston
Author-email: nick@koston.org
License: Apache Software License 2.0
Keywords: aiolip
Platform: UNKNOWN
Classifier: Development Status :: 2 - Pre-Alpha
Classifier: Intended Audience :: Developers
Classifier: License :: OSI Approved :: Apache Software License
Classifier: Natural Language :: English
Classifier: Programming Language :: Python :: 3
Classifier: Programming Language :: Python :: 3.5
Classifier: Programming Language :: Python :: 3.6
Classifier: Programming Language :: Python :: 3.7
Classifier: Programming Language :: Python :: 3.8
Requires-Python: >=3.5
